{
  "000001": [
    83,
    50,
    16,
    92,
    84,
    99
  ],
  "000002": [
    60,
    38,
    20,
    50,
    40,
    59
  ],
  "000058": [
    79,
    86,
    25,
    81,
    9,
    100
  ],
  "000152": [
    58,
    82,
    30,
    17,
    90,
    35
  ],
  "000155": [
    80,
    81,
    25,
    79,
    87,
    100
  ],
  "000054": [
    81,
    63,
    26,
    80,
    100,
    82
  ],
  "000005": [
    95,
    50,
    16,
    87,
    93,
    59
  ],
  "000006": [
    70,
    78,
    21,
    85,
    87,
    82
  ],
  "000007": [
    64,
    63,
    82,
    6,
    0,
    28
  ],
  "000009": [
    87,
    50,
    19,
    79,
    38,
    81
  ],
  "000010": [
    94,
    64,
    13,
    89,
    87,
    82
  ],
  "000013": [
    82,
    83,
    30,
    0,
    100,
    38
  ],
  "000014": [
    70,
    75,
    11,
    60,
    0,
    31
  ],
  "000015": [
    31,
    50,
    80,
    18,
    59,
    50
  ],
  "000016": [
    61,
    67,
    67,
    31,
    31,
    30
  ],
  "000018": [
    57,
    85,
    28,
    73,
    96,
    82
  ],
  "000020": [
    38,
    50,
    76,
    15,
    37,
    68
  ],
  "000023": [
    64,
    55,
    74,
    31,
    50,
    31
  ],
  "000025": [
    57,
    59,
    65,
    19,
    16,
    25
  ],
  "000028": [
    65,
    42,
    21,
    96,
    79,
    100
  ],
  "000029": [
    72,
    74,
    28,
    70,
    100,
    85
  ],
  "000030": [
    65,
    57,
    81,
    16,
    98,
    42
  ],
  "000031": [
    59,
    65,
    33,
    67,
    50,
    36
  ],
  "000032": [
    34,
    50,
    54,
    20,
    67,
    43
  ],
  "000035": [
    100,
    40,
    20,
    93,
    25,
    100
  ],
  "000037": [
    58,
    77,
    65,
    11,
    31,
    0
  ],
  "000038": [
    46,
    50,
    69,
    25,
    65,
    31
  ],
  "000040": [
    100,
    50,
    28,
    76,
    19,
    38
  ],
  "000041": [
    54,
    50,
    72,
    28,
    0,
    33
  ],
  "000042": [
    67,
    51,
    26,
    87,
    70,
    60
  ],
  "000043": [
    72,
    58,
    16,
    70,
    76,
    81
  ],
  "000044": [
    67,
    84,
    35,
    72,
    0,
    100
  ],
  "000045": [
    65,
    60,
    28,
    77,
    40,
    100
  ],
  "000047": [
    69,
    65,
    50,
    82,
    9,
    100
  ],
  "000048": [
    31,
    89,
    42,
    16,
    1,
    31
  ],
  "000050": [
    39,
    54,
    63,
    31,
    31,
    31
  ],
  "000051": [
    64,
    84,
    74,
    24,
    0,
    0
  ],
  "000052": [
    31,
    62,
    64,
    29,
    20,
    65
  ],
  "000055": [
    54,
    72,
    70,
    17,
    0,
    38
  ],
  "000056": [
    61,
    77,
    55,
    89,
    0,
    69
  ],
  "000060": [
    33,
    100,
    65,
    15,
    0,
    0
  ],
  "000064": [
    36,
    77,
    55,
    25,
    45,
    38
  ],
  "000065": [
    55,
    76,
    64,
    23,
    0,
    37
  ],
  "000068": [
    34,
    64,
    63,
    18,
    26,
    0
  ],
  "000069": [
    35,
    62,
    70,
    14,
    9,
    25
  ],
  "000071": [
    74,
    69,
    35,
    82,
    89,
    59
  ],
  "000073": [
    65,
    61,
    33,
    83,
    37,
    96
  ],
  "000076": [
    60,
    67,
    59,
    16,
    0,
    56
  ],
  "000077": [
    80,
    67,
    30,
    81,
    47,
    100
  ],
  "000078": [
    76,
    79,
    16,
    98,
    35,
    93
  ],
  "000079": [
    38,
    21,
    60,
    9,
    30,
    0
  ],
  "000080": [
    28,
    55,
    68,
    20,
    0,
    33
  ],
  "000081": [
    37,
    65,
    62,
    9,
    0,
    25
  ],
  "000083": [
    65,
    84,
    28,
    83,
    60,
    94
  ],
  "000085": [
    72,
    69,
    29,
    70,
    60,
    96
  ],
  "000086": [
    55,
    72,
    29,
    74,
    78,
    35
  ],
  "000088": [
    67,
    67,
    34,
    94,
    74,
    75
  ],
  "000091": [
    50,
    70,
    70,
    4,
    0,
    33
  ],
  "000092": [
    64,
    44,
    40,
    98,
    81,
    64
  ],
  "000096": [
    72,
    82,
    33,
    82,
    25,
    100
  ],
  "000097": [
    67,
    55,
    31,
    82,
    69,
    70
  ],
  "000099": [
    69,
    48,
    35,
    83,
    76,
    84
  ],
  "000100": [
    60,
    67,
    30,
    92,
    90,
    36
  ],
  "000103": [
    70,
    76,
    26,
    80,
    18,
    70
  ],
  "000104": [
    41,
    57,
    55,
    15,
    74,
    39
  ],
  "000106": [
    67,
    50,
    37,
    85,
    70,
    67
  ],
  "000108": [
    65,
    70,
    30,
    82,
    100,
    85
  ],
  "000109": [
    34,
    63,
    57,
    12,
    67,
    38
  ],
  "000110": [
    90,
    68,
    26,
    89,
    82,
    72
  ],
  "000111": [
    62,
    68,
    33,
    74,
    86,
    65
  ],
  "000114": [
    64,
    21,
    25,
    9,
    21,
    33
  ],
  "000115": [
    50,
    26,
    68,
    15,
    81,
    0
  ],
  "000116": [
    33,
    63,
    37,
    25,
    59,
    40
  ],
  "000117": [
    75,
    30,
    31,
    77,
    0,
    100
  ],
  "000118": [
    86,
    67,
    33,
    65,
    36,
    72
  ],
  "000161": [
    65,
    77,
    28,
    82,
    28,
    91
  ],
  "000160": [
    70,
    65,
    72,
    11,
    14,
    30
  ],
  "000157": [
    67,
    81,
    33,
    77,
    97,
    83
  ],
  "000156": [
    70,
    58,
    28,
    86,
    89,
    30
  ],
  "000153": [
    65,
    55,
    84,
    13,
    48,
    28
  ],
  "000151": [
    55,
    76,
    31,
    59,
    1,
    81
  ],
  "000150": [
    50,
    31,
    64,
    52,
    80,
    63
  ],
  "000148": [
    50,
    72,
    21,
    76,
    7,
    35
  ],
  "000147": [
    59,
    65,
    38,
    96,
    87,
    94
  ],
  "000146": [
    73,
    57,
    33,
    77,
    29,
    83
  ],
  "000145": [
    43,
    67,
    34,
    80,
    7,
    100
  ],
  "000143": [
    53,
    16,
    55,
    3,
    64,
    29
  ],
  "000142": [
    60,
    25,
    38,
    72,
    65,
    100
  ],
  "000140": [
    70,
    79,
    34,
    64,
    99,
    100
  ],
  "000137": [
    40,
    72,
    65,
    8,
    33,
    0
  ],
  "000135": [
    42,
    50,
    58,
    6,
    0,
    31
  ],
  "000134": [
    48,
    29,
    58,
    0,
    0,
    1
  ],
  "000133": [
    64,
    70,
    21,
    87,
    77,
    64
  ],
  "000132": [
    58,
    84,
    42,
    78,
    0,
    95
  ],
  "000131": [
    65,
    65,
    39,
    75,
    0,
    100
  ],
  "000129": [
    40,
    65,
    60,
    6,
    15,
    65
  ],
  "000126": [
    77,
    23,
    43,
    76,
    98,
    100
  ],
  "000125": [
    31,
    65,
    72,
    0,
    50,
    0
  ],
  "000122": [
    61,
    59,
    33,
    87,
    93,
    39
  ],
  "000121": [
    76,
    48,
    35,
    74,
    31,
    100
  ]
}

